{
	"editor": {
		"allAngles": false,
		"singleTexture": false
	},
	"textureWidth": 16,
	"textureHeight": 16,
	"textures": {
	},
	"elements": [
		{
			"name": "base",
			"from": [ 0.0, 0.0, 0.0 ], 
			"to": [ 16.0, 1.0, 16.0 ], 
			"faces": {
				"north": { "texture": "#ceramic", "uv": [ 0.0, 0.0, 16.0, 1.0 ] },
				"east": { "texture": "#ceramic", "uv": [ 0.0, 0.0, 16.0, 1.0 ] },
				"south": { "texture": "#ceramic", "uv": [ 0.0, 0.0, 16.0, 1.0 ] },
				"west": { "texture": "#ceramic", "uv": [ 0.0, 0.0, 16.0, 1.0 ] },
				"up": { "texture": "#ceramic", "uv": [ 0.0, 0.0, 16.0, 16.0 ] },
				"down": { "texture": "#ceramic", "uv": [ 0.0, 0.0, 16.0, 16.0 ] }
			}
		},
		{
			"name": "Cube",
			"from": [ 0.0, 1.0, 0.0 ], 
			"to": [ 16.0, 2.0, 1.0 ], 
			"rotationOrigin": [ 0.0, 1.0, 0.0 ],
			"faces": {
				"north": { "texture": "#ceramic", "uv": [ 0.0, 0.0, 16.0, 1.0 ] },
				"east": { "texture": "#ceramic", "uv": [ 0.0, 0.0, 1.0, 1.0 ] },
				"south": { "texture": "#ceramic", "uv": [ 0.0, 0.0, 16.0, 1.0 ] },
				"west": { "texture": "#ceramic", "uv": [ 0.0, 0.0, 1.0, 1.0 ] },
				"up": { "texture": "#ceramic", "uv": [ 0.0, 0.0, 16.0, 1.0 ] },
				"down": { "texture": "#ceramic", "uv": [ 0.0, 0.0, 16.0, 1.0 ] }
			}
		},
		{
			"name": "Cube3",
			"from": [ 0.0, 1.0, 15.0 ], 
			"to": [ 16.0, 2.0, 16.0 ], 
			"rotationOrigin": [ 0.0, 1.0, 15.0 ],
			"faces": {
				"north": { "texture": "#ceramic", "uv": [ 0.0, 0.0, 16.0, 1.0 ] },
				"east": { "texture": "#ceramic", "uv": [ 0.0, 0.0, 1.0, 1.0 ] },
				"south": { "texture": "#ceramic", "uv": [ 0.0, 0.0, 16.0, 1.0 ] },
				"west": { "texture": "#ceramic", "uv": [ 0.0, 0.0, 1.0, 1.0 ] },
				"up": { "texture": "#ceramic", "uv": [ 0.0, 0.0, 16.0, 1.0 ] },
				"down": { "texture": "#ceramic", "uv": [ 0.0, 0.0, 16.0, 1.0 ] }
			}
		},
		{
			"name": "Cube1",
			"from": [ 0.0, 1.0, 1.0 ], 
			"to": [ 1.0, 2.0, 15.0 ], 
			"rotationOrigin": [ 0.0, 1.0, 1.0 ],
			"faces": {
				"north": { "texture": "#ceramic", "uv": [ 0.0, 0.0, 1.0, 1.0 ] },
				"east": { "texture": "#ceramic", "uv": [ 0.0, 0.0, 14.0, 1.0 ] },
				"south": { "texture": "#ceramic", "uv": [ 0.0, 0.0, 1.0, 1.0 ] },
				"west": { "texture": "#ceramic", "uv": [ 0.0, 0.0, 14.0, 1.0 ] },
				"up": { "texture": "#ceramic", "uv": [ 0.0, 0.0, 1.0, 14.0 ] },
				"down": { "texture": "#ceramic", "uv": [ 0.0, 0.0, 1.0, 14.0 ] }
			}
		},
		{
			"name": "Cube5",
			"from": [ 15.0, 1.0, 1.0 ], 
			"to": [ 16.0, 2.0, 15.0 ], 
			"rotationOrigin": [ 15.0, 1.0, 1.0 ],
			"faces": {
				"north": { "texture": "#ceramic", "uv": [ 0.0, 0.0, 1.0, 1.0 ] },
				"east": { "texture": "#ceramic", "uv": [ 0.0, 0.0, 14.0, 1.0 ] },
				"south": { "texture": "#ceramic", "uv": [ 0.0, 0.0, 1.0, 1.0 ] },
				"west": { "texture": "#ceramic", "uv": [ 0.0, 0.0, 14.0, 1.0 ] },
				"up": { "texture": "#ceramic", "uv": [ 0.0, 0.0, 1.0, 14.0 ] },
				"down": { "texture": "#ceramic", "uv": [ 0.0, 0.0, 1.0, 14.0 ] }
			}
		},
		{
			"name": "Cube6",
			"from": [ 11.0, 1.0, 1.0 ], 
			"to": [ 12.0, 2.0, 4.0 ], 
			"rotationOrigin": [ 11.0, 1.0, 1.0 ],
			"faces": {
				"north": { "texture": "#ceramic", "uv": [ 0.0, 0.0, 1.0, 1.0 ] },
				"east": { "texture": "#ceramic", "uv": [ 0.0, 0.0, 3.0, 1.0 ] },
				"south": { "texture": "#ceramic", "uv": [ 0.0, 0.0, 1.0, 1.0 ] },
				"west": { "texture": "#ceramic", "uv": [ 0.0, 0.0, 3.0, 1.0 ] },
				"up": { "texture": "#ceramic", "uv": [ 0.0, 0.0, 1.0, 3.0 ] },
				"down": { "texture": "#ceramic", "uv": [ 0.0, 0.0, 1.0, 3.0 ] }
			}
		},
		{
			"name": "Cube8",
			"from": [ 7.0, 1.0, 1.0 ], 
			"to": [ 8.0, 2.0, 15.0 ], 
			"rotationOrigin": [ 7.0, 1.0, 1.0 ],
			"faces": {
				"north": { "texture": "#ceramic", "uv": [ 0.0, 0.0, 1.0, 1.0 ] },
				"east": { "texture": "#ceramic", "uv": [ 0.0, 0.0, 14.0, 1.0 ] },
				"south": { "texture": "#ceramic", "uv": [ 0.0, 0.0, 1.0, 1.0 ] },
				"west": { "texture": "#ceramic", "uv": [ 0.0, 0.0, 14.0, 1.0 ] },
				"up": { "texture": "#ceramic", "uv": [ 0.0, 0.0, 1.0, 14.0 ] },
				"down": { "texture": "#ceramic", "uv": [ 0.0, 0.0, 1.0, 14.0 ] }
			}
		},
		{
			"name": "Cube9",
			"from": [ 1.0, 1.0, 7.0 ], 
			"to": [ 7.0, 2.0, 9.0 ], 
			"rotationOrigin": [ 1.0, 1.0, 7.0 ],
			"faces": {
				"north": { "texture": "#ceramic", "uv": [ 0.0, 0.0, 6.0, 1.0 ] },
				"east": { "texture": "#ceramic", "uv": [ 0.0, 0.0, 2.0, 1.0 ] },
				"south": { "texture": "#ceramic", "uv": [ 0.0, 0.0, 6.0, 1.0 ] },
				"west": { "texture": "#ceramic", "uv": [ 0.0, 0.0, 2.0, 1.0 ] },
				"up": { "texture": "#ceramic", "uv": [ 0.0, 0.0, 6.0, 2.0 ] },
				"down": { "texture": "#ceramic", "uv": [ 0.0, 0.0, 6.0, 2.0 ] }
			}
		},
		{
			"name": "Cube10",
			"from": [ 8.0, 1.0, 4.0 ], 
			"to": [ 15.0, 2.0, 15.0 ], 
			"rotationOrigin": [ 8.0, 1.0, 4.0 ],
			"faces": {
				"north": { "texture": "#ceramic", "uv": [ 0.0, 0.0, 7.0, 1.0 ] },
				"east": { "texture": "#ceramic", "uv": [ 0.0, 0.0, 11.0, 1.0 ] },
				"south": { "texture": "#ceramic", "uv": [ 0.0, 0.0, 7.0, 1.0 ] },
				"west": { "texture": "#ceramic", "uv": [ 0.0, 0.0, 11.0, 1.0 ] },
				"up": { "texture": "#ceramic", "uv": [ 0.0, 0.0, 7.0, 11.0 ] },
				"down": { "texture": "#ceramic", "uv": [ 0.0, 0.0, 7.0, 11.0 ] }
			}
		}
	]}